streamlit_cookie_manager/__init__.py
streamlit_cookie_manager/manager.py
streamlit_cookie_manager/frontend/dist/index.html
streamlit_cookie_manager/frontend/dist/vite.svg
streamlit_cookie_manager/frontend/dist/assets/index-BFixdUHd.js
streamlit_cookie_manager/frontend/node_modules/flatted/python/flatted.py
streamlit_cookie_manager-0.1.4.dist-info/licenses/LICENSE
streamlit_cookie_manager-0.1.4.dist-info/METADATA
streamlit_cookie_manager-0.1.4.dist-info/WHEEL
streamlit_cookie_manager-0.1.4.dist-info/top_level.txt
streamlit_cookie_manager-0.1.4.dist-info/RECORD
