Metadata-Version: 2.4
Name: streamlit-cookie-manager
Version: 0.1.4
Summary: A Streamlit component to manage encrypted cookies in the browser
Home-page: https://github.com/jasonisdoing/streamlit-cookie-manager
Author: Jason Kim
Author-email: Jason Kim <kimwootak@catholic.ac.kr>
License: MIT License
Classifier: Development Status :: 3 - Alpha
Classifier: Intended Audience :: Developers
Classifier: License :: OSI Approved :: MIT License
Classifier: Programming Language :: Python :: 3
Classifier: Programming Language :: Python :: 3.8
Classifier: Programming Language :: Python :: 3.9
Classifier: Programming Language :: Python :: 3.10
Classifier: Programming Language :: Python :: 3.11
Classifier: Topic :: Software Development :: Libraries :: Python Modules
Classifier: Topic :: Internet :: WWW/HTTP :: Dynamic Content
Requires-Python: >=3.8
License-File: LICENSE
Requires-Dist: streamlit>=1.20
Requires-Dist: cryptography>=41.0.0
Dynamic: author
Dynamic: home-page
Dynamic: license-file
Dynamic: requires-python
